spoton_soozaccess/__init__.py
spoton_soozaccess/__main__.py
spoton_soozaccess/alarms_helper.py
spoton_soozaccess/config_helper.py
spoton_soozaccess/enterprise_helper.py
spoton_soozaccess/factor_helper.py
spoton_soozaccess/group_helper.py
spoton_soozaccess/group_member_helper.py
spoton_soozaccess/level_helper.py
spoton_soozaccess/logger.py
spoton_soozaccess/response_helper.py
spoton_soozaccess/response_option_helper.py
spoton_soozaccess/rules_helper.py
spoton_soozaccess/soozaccess.py
spoton_soozaccess/statistics_helper.py
spoton_soozaccess/theme_helper.py
spoton_soozaccess/user_helper.py
spoton_soozaccess-0.3.3.dist-info/METADATA
spoton_soozaccess-0.3.3.dist-info/WHEEL
spoton_soozaccess-0.3.3.dist-info/top_level.txt
spoton_soozaccess-0.3.3.dist-info/RECORD
