Metadata-Version: 2.1
Name: spoton-soozaccess
Version: 0.3.3
Summary: A tool to access Spot-On API using Python
Home-page: https://gitlab.forge.hefr.ch/pa-spot-on-demeusy/spot-on-soozaccess
Author: Jean Demeusy
Author-email: dev.jdu@gmail.com
License: UNKNOWN
Platform: UNKNOWN
Classifier: Programming Language :: Python :: 3
Classifier: License :: OSI Approved :: MIT License
Classifier: Operating System :: OS Independent
Requires-Dist: click
Requires-Dist: requests
